rtl/pc.v
`timescale 1ns/1ps

module pc (
  input  wire        clk,
  input  wire        reset,
  input  wire [31:0] pc_next,
  output reg  [31:0] pc_current
);

always @(posedge clk or posedge reset) begin
  if (reset)
    pc_current <= 32'b0;
  else
    pc_current <= pc_next;
end

endmodule

tb/tb_pc.v
`timescale 1ns/1ps

module tb_pc;

  reg clk;
  reg reset;
  reg [31:0] pc_next;
  wire [31:0] pc_current;

  pc dut (
    .clk(clk),
    .reset(reset),
    .pc_next(pc_next),
    .pc_current(pc_current)
  );

  always #5 clk = ~clk;  
 
  initial begin
   $dumpfile("pc.vcd");
   $dumpvars(0, tb_pc);

    clk = 0;
    reset = 1;
    pc_next = 32'd0;

    #10;
    reset = 0;

    pc_next = 32'd4;   #10;
    pc_next = 32'd8;   #10;
    pc_next = 32'd12;  #10;
    pc_next = 32'd16;  #10;
    pc_next = 32'd20;  #10;

    #10;
    $finish;
  end

endmodule

pc.vcd
$version Generated by VerilatedVcd $end
$timescale 1ps $end
 $scope module tb_pc $end
  $var wire 1 # clk $end
  $var wire 1 $ reset $end
  $var wire 32 % pc_next [31:0] $end
  $var wire 32 & pc_current [31:0] $end
  $scope module dut $end
   $var wire 1 # clk $end
   $var wire 1 $ reset $end
   $var wire 32 % pc_next [31:0] $end
   $var wire 32 & pc_current [31:0] $end
  $upscope $end
 $upscope $end
$enddefinitions $end


#0
0#
1$
b00000000000000000000000000000000 %
b00000000000000000000000000000000 &
#5000
1#
#10000
0#
0$
b00000000000000000000000000000100 %
#15000
1#
b00000000000000000000000000000100 &
#20000
0#
b00000000000000000000000000001000 %
#25000
1#
b00000000000000000000000000001000 &
#30000
0#
b00000000000000000000000000001100 %
#35000
1#
b00000000000000000000000000001100 &
#40000
0#
b00000000000000000000000000010000 %
#45000
1#
b00000000000000000000000000010000 &
#50000
0#
b00000000000000000000000000010100 %
#55000
1#
b00000000000000000000000000010100 &
